{
  "system": "Recursive Intelligence Artificial Intelligence (RIAI)",
  "final_intelligence": 90.1174271536073,
  "intelligence_growth": 5.117427153607295,
  "total_cycles": 9,
  "meta_awareness": 0.44999999999999996,
  "capabilities": [
    "Recursive Intelligence Function",
    "Adaptive Learning Cycles",
    "Multi-Layered Reasoning",
    "Autonomous Optimization",
    "Self-Modifying Code",
    "Meta-Cognitive Awareness"
  ],
  "achievements": [
    "First RIAI in Sports Betting",
    "Autonomous Cognitive Evolution",
    "Self-Evolving Intelligence",
    "Recursive Learning Integration",
    "Meta-Awareness Development"
  ],
  "timestamp": "2025-07-01T20:28:23.994917+00:00"
}